{"ref":"94499e11-ab95-49a1-b458-aa857a952b53","syncData":{"version":2,"machineId":"9759d5c3-4c0f-4b3c-ab4f-a0a8ebbc6be1","content":"{\"windows\":\"// Place your key bindings in this file to override the defaults\\n[\\n\\t{ // make cursor back to active editor group\\n\\t\\t\\\"key\\\": \\\"ctrl+shift+c\\\",\\n\\t\\t\\\"command\\\": \\\"workbench.action.focusActiveEditorGroup\\\",\\n\\t\\t// \\\"when\\\": \\\"!terminalFocus\\\"\\n\\t},\\n\\t{ // make cursor back to first editor group\\n\\t\\t\\\"key\\\": \\\"ctrl+1\\\",\\n\\t\\t\\\"command\\\": \\\"workbench.action.focusFirstEditorGroup\\\"\\n\\t},\\n\\t//------- move window -----------\\n\\t{ // window move down\\n\\t\\t\\\"key\\\": \\\"ctrl+j\\\",\\n\\t\\t\\\"command\\\": \\\"vim.remap\\\",\\n\\t\\t\\\"when\\\": \\\"vim.mode == 'Normal' && !suggestWidgetVisible && !inQuickOpen\\\",\\n\\t\\t\\\"args\\\": {\\n\\t\\t\\t\\\"after\\\": [\\n\\t\\t\\t\\t\\\"<c-w>\\\",\\n\\t\\t\\t\\t\\\"j\\\"\\n\\t\\t\\t],\\n\\t\\t}\\n\\t},\\n\\t{ // move up\\n\\t\\t\\\"key\\\": \\\"ctrl+k\\\",\\n\\t\\t\\\"command\\\": \\\"vim.remap\\\",\\n\\t\\t\\\"when\\\": \\\"vim.mode == 'Normal' && !suggestWidgetVisible && !inQuickOpen && !panelFocus\\\",\\n\\t\\t\\\"args\\\": {\\n\\t\\t\\t\\\"after\\\": [\\n\\t\\t\\t\\t\\\"<c-w>\\\",\\n\\t\\t\\t\\t\\\"k\\\"\\n\\t\\t\\t],\\n\\t\\t}\\n\\t},\\n\\t{ // window move left\\n\\t\\t\\\"key\\\": \\\"ctrl+h\\\",\\n\\t\\t\\\"command\\\": \\\"vim.remap\\\",\\n\\t\\t\\\"when\\\": \\\"vim.mode == 'Normal' && !suggestWidgetVisible && !inQuickOpen && !panelFocus\\\",\\n\\t\\t\\\"args\\\": {\\n\\t\\t\\t\\\"after\\\": [\\n\\t\\t\\t\\t\\\"<c-w>\\\",\\n\\t\\t\\t\\t\\\"h\\\"\\n\\t\\t\\t],\\n\\t\\t}\\n\\t},\\n\\t{ // window move right\\n\\t\\t\\\"key\\\": \\\"ctrl+l\\\",\\n\\t\\t\\\"command\\\": \\\"vim.remap\\\",\\n\\t\\t\\\"when\\\": \\\"vim.mode == 'Normal' && !suggestWidgetVisible && !inQuickOpen\\\",\\n\\t\\t\\\"args\\\": {\\n\\t\\t\\t\\\"after\\\": [\\n\\t\\t\\t\\t\\\"<c-w>\\\",\\n\\t\\t\\t\\t\\\"l\\\"\\n\\t\\t\\t],\\n\\t\\t}\\n\\t},\\n\\t// -----file explorer start------\\n\\t{ // open file explorer use which key\\n\\t\\t\\\"key\\\": \\\"e\\\",\\n\\t\\t\\\"command\\\": \\\"whichkey.triggerKey\\\",\\n\\t\\t\\\"when\\\": \\\"whichkeyVisible && sideBarVisible && explorerViewletVisible\\\",\\n\\t\\t\\\"args\\\": {\\n\\t\\t\\t\\\"key\\\": \\\"e\\\",\\n\\t\\t\\t\\\"when\\\": \\\"sideBarVisible && explorerViewletVisible\\\"\\n\\t\\t},\\n\\t},\\n\\t{ // rename file\\n\\t\\t\\\"key\\\": \\\"r\\\",\\n\\t\\t\\\"command\\\": \\\"renameFile\\\",\\n\\t\\t\\\"when\\\": \\\"explorerViewletVisible && filesExplorerFocus && !explorerResourceIsRoot && !explorerResourceReadonly && !inputFocus\\\"\\n\\t},\\n\\t{ // disable old style rename shortcut\\n\\t\\t\\\"key\\\": \\\"enter\\\",\\n\\t\\t\\\"command\\\": \\\"-renameFile\\\",\\n\\t\\t\\\"when\\\": \\\"explorerViewletVisible && filesExplorerFocus && !explorerResourceIsRoot && !explorerResourceReadonly && !inputFocus\\\"\\n\\t},\\n\\t{ // move down\\n\\t\\t\\\"key\\\": \\\"j\\\",\\n\\t\\t\\\"command\\\": \\\"list.focusDown\\\",\\n\\t\\t\\\"when\\\": \\\"explorerViewletVisible && filesExplorerFocus && !explorerResourceIsRoot && !explorerResourceReadonly && !inputFocus\\\"\\n\\t},\\n\\t{ // move up\\n\\t\\t\\\"key\\\": \\\"k\\\",\\n\\t\\t\\\"command\\\": \\\"list.focusUp\\\",\\n\\t\\t\\\"when\\\": \\\"explorerViewletVisible && filesExplorerFocus && !explorerResourceIsRoot && !explorerResourceReadonly && !inputFocus\\\"\\n\\t},\\n\\t// -----file explorer end------\\n\\t// -----suggest item start------\\n\\t{ // move down at auto completion prompt\\n\\t\\t\\\"key\\\": \\\"ctrl+j\\\",\\n\\t\\t\\\"command\\\": \\\"selectNextSuggestion\\\",\\n\\t\\t\\\"when\\\": \\\"editorTextFocus && suggestWidgetMultipleSuggestions && suggestWidgetVisible\\\"\\n\\t},\\n\\t{ // move up at auto completion prompt\\n\\t\\t\\\"key\\\": \\\"ctrl+k\\\",\\n\\t\\t\\\"command\\\": \\\"selectPrevSuggestion\\\",\\n\\t\\t\\\"when\\\": \\\"editorTextFocus && suggestWidgetMultipleSuggestions && suggestWidgetVisible\\\"\\n\\t},\\n\\t{ // move up at quick open\\n\\t\\t\\\"key\\\": \\\"ctrl+k\\\",\\n\\t\\t\\\"command\\\": \\\"workbench.action.quickOpenNavigatePrevious\\\",\\n\\t\\t\\\"when\\\": \\\"inQuickOpen\\\"\\n\\t},\\n\\t{ // move down at problem open\\n\\t\\t\\\"key\\\": \\\"ctrl+shift+j\\\",\\n\\t\\t\\\"command\\\": \\\"list.focusDown\\\",\\n\\t\\t\\\"when\\\": \\\"panelFocus && activePanel == 'workbench.panel.markers' \\\"\\n\\t},\\n\\t{ // move up at problem open\\n\\t\\t\\\"key\\\": \\\"ctrl+shift+k\\\",\\n\\t\\t\\\"command\\\": \\\"list.focusUp\\\",\\n\\t\\t\\\"when\\\": \\\"panelFocus && activePanel == 'workbench.panel.markers' \\\"\\n\\t},\\n\\t{\\n\\t\\t\\\"key\\\": \\\"tab\\\",\\n\\t\\t\\\"command\\\": \\\"selectNextSuggestion\\\",\\n\\t\\t\\\"when\\\": \\\"editorTextFocus && suggestWidgetMultipleSuggestions && suggestWidgetVisible\\\"\\n\\t},\\n\\t{\\n\\t\\t\\\"key\\\": \\\"shift+tab\\\",\\n\\t\\t\\\"command\\\": \\\"selectPrevSuggestion\\\",\\n\\t\\t\\\"when\\\": \\\"editorTextFocus && suggestWidgetMultipleSuggestions && suggestWidgetVisible\\\"\\n\\t},\\n\\t{\\n\\t\\t\\\"key\\\": \\\"shift+tab\\\",\\n\\t\\t\\\"command\\\": \\\"workbench.action.quickOpenNavigatePrevious\\\",\\n\\t\\t\\\"when\\\": \\\"inQuickOpen\\\"\\n\\t},\\n\\t{ // new file\\n\\t\\t\\\"key\\\": \\\"a\\\",\\n\\t\\t\\\"command\\\": \\\"explorer.newFile\\\",\\n\\t\\t\\\"when\\\": \\\"filesExplorerFocus && !inputFocus\\\"\\n\\t},\\n\\t{ // new folder\\n\\t\\t\\\"key\\\": \\\"shift+a\\\",\\n\\t\\t\\\"command\\\": \\\"explorer.newFolder\\\",\\n\\t\\t\\\"when\\\": \\\"filesExplorerFocus && !inputFocus\\\"\\n\\t},\\n\\t{ // delete file or folder\\n\\t\\t\\\"key\\\": \\\"d\\\",\\n\\t\\t\\\"command\\\": \\\"deleteFile\\\",\\n\\t\\t\\\"when\\\": \\\"explorerViewletVisible && filesExplorerFocus && !explorerResourceReadonly && !inputFocus\\\"\\n\\t},\\n\\t{ // toggle terminal\\n\\t\\t\\\"key\\\": \\\"ctrl+oem_5\\\",\\n\\t\\t\\\"command\\\": \\\"workbench.action.terminal.toggleTerminal\\\",\\n\\t\\t\\\"when\\\": \\\"terminal.active\\\"\\n\\t},\\n\\t{ // maxmize terminal\\n\\t\\t\\\"key\\\": \\\"ctrl+m\\\",\\n\\t\\t\\\"command\\\": \\\"workbench.action.toggleMaximizedPanel\\\",\\n\\t\\t\\\"when\\\": \\\"terminalFocus\\\"\\n\\t},\\n\\t{ // find & replace\\n\\t\\t\\\"key\\\": \\\"ctrl+f\\\",\\n\\t\\t\\\"command\\\": \\\"editor.action.startFindReplaceAction\\\",\\n\\t\\t\\\"when\\\": \\\"editorFocus || editorIsOpen\\\"\\n\\t},\\n\\t{ // 取消快捷键原本的绑定，即第二个标签页\\n\\t\\t\\\"key\\\": \\\"alt+2\\\",\\n\\t\\t\\\"command\\\": \\\"-workbench.action.openEditorAtIndex2\\\"\\n\\t},\\n\\t{ // 打开辅助栏\\n\\t\\t\\\"key\\\": \\\"alt+2\\\",\\n\\t\\t\\\"command\\\": \\\"workbench.action.toggleAuxiliaryBar\\\"\\n\\t}\\n]\"}"}}